neuromllite/ArborHandler.py
neuromllite/BBPConnectomeReader.py
neuromllite/BindsNETHandler.py
neuromllite/ConnectivityHandler.py
neuromllite/DefaultNetworkHandler.py
neuromllite/GraphVizHandler.py
neuromllite/MDFHandler.py
neuromllite/MatrixHandler.py
neuromllite/NetworkGenerator.py
neuromllite/NeuronHandler.py
neuromllite/PsyNeuLinkHandler.py
neuromllite/PsyNeuLinkReader.py
neuromllite/PyNNHandler.py
neuromllite/SonataHandler.py
neuromllite/SonataReader.py
neuromllite/__init__.py
neuromllite/utils.py
neuromllite/gui/NMLliteUI.py
neuromllite/gui/__init__.py
neuromllite/sweep/GenerateTests.py
neuromllite/sweep/ParameterSweep.py
neuromllite/sweep/__init__.py
neuromllite-0.6.1.dist-info/licenses/LICENSE.lesser
neuromllite-0.6.1.dist-info/METADATA
neuromllite-0.6.1.dist-info/WHEEL
neuromllite-0.6.1.dist-info/entry_points.txt
neuromllite-0.6.1.dist-info/top_level.txt
neuromllite-0.6.1.dist-info/RECORD
