Metadata-Version: 2.4
Name: neuromllite
Version: 0.6.1
Summary: A common JSON/YAML based format for compact network specification, closely tied to NeuroML v2
Home-page: https://github.com/NeuroML/NeuroMLlit
Author: Padraig Gleeson
Author-email: p.gleeson@gmail.com
License: LGPL-3.0-only
Classifier: Intended Audience :: Science/Research
Classifier: Natural Language :: English
Classifier: Operating System :: OS Independent
Classifier: Programming Language :: Python :: 3.9
Classifier: Programming Language :: Python :: 3.10
Classifier: Programming Language :: Python :: 3.11
Classifier: Programming Language :: Python :: 3.12
Classifier: Programming Language :: Python :: 3.13
Classifier: Topic :: Scientific/Engineering
License-File: LICENSE.lesser
Requires-Dist: libNeuroML>=0.5.1
Requires-Dist: pyyaml
Requires-Dist: numpy
Requires-Dist: tables
Requires-Dist: h5py
Requires-Dist: modelspec>=0.2.6
Requires-Dist: ppft[dill]
Provides-Extra: extras
Requires-Dist: pyNN; extra == "extras"
Requires-Dist: bmtk; extra == "extras"
Requires-Dist: matplotlib; extra == "extras"
Requires-Dist: PyQt5; extra == "extras"
Requires-Dist: pyneuroml; extra == "extras"
Requires-Dist: pyelectro; extra == "extras"
Requires-Dist: neuron; extra == "extras"
Requires-Dist: h5py; extra == "extras"
Requires-Dist: graphviz; extra == "extras"
Provides-Extra: all
Requires-Dist: neuromllite[extras]; extra == "all"
Provides-Extra: dev
Requires-Dist: neuromllite[all]; extra == "dev"
Requires-Dist: neuromllite[doc]; extra == "dev"
Requires-Dist: pytest; extra == "dev"
Requires-Dist: pytest-xdist; extra == "dev"
Requires-Dist: pre-commit; extra == "dev"
Provides-Extra: doc
Requires-Dist: sphinxcontrib-bibtex; extra == "doc"
Requires-Dist: bmtk; extra == "doc"
Requires-Dist: matplotlib; extra == "doc"
Requires-Dist: PyQt5; extra == "doc"
Requires-Dist: pyneuroml; extra == "doc"
Requires-Dist: pyelectro; extra == "doc"
Requires-Dist: numpy; extra == "doc"
Requires-Dist: neuron; extra == "doc"
Requires-Dist: h5py; extra == "doc"
Requires-Dist: graphviz; extra == "doc"
Requires-Dist: pylems; extra == "doc"
Requires-Dist: tables; extra == "doc"
Requires-Dist: arbor==0.9.0; extra == "doc"
Dynamic: license-file
